<?xml version="1.0" encoding="UTF-8" standalone="yes"?>
<worksheet xmlns="http://schemas.openxmlformats.org/spreadsheetml/2006/main" xmlns:r="http://schemas.openxmlformats.org/officeDocument/2006/relationships"><sheetPr filterMode="false"><pageSetUpPr fitToPage="false"/></sheetPr><dimension ref="A1"/><sheetViews><sheetView windowProtection="false" showFormulas="false" showGridLines="true" showRowColHeaders="true" showZeros="true" rightToLeft="false" tabSelected="false" showOutlineSymbols="true" defaultGridColor="true" view="normal" topLeftCell="A1" colorId="64" zoomScale="100" zoomScaleNormal="100" zoomScalePageLayoutView="100" workbookViewId="0"><selection pane="topLeft" activeCell="S4" activeCellId="0" sqref="S4"/></sheetView></sheetViews><sheetFormatPr defaultRowHeight="12.8"></sheetFormatPr><cols><col collapsed="false" hidden="false" max="1" min="1" style="0" width="8.50510204081633"/><col collapsed="false" hidden="false" max="2" min="2" style="0" width="12.9591836734694"/><col collapsed="false" hidden="false" max="1025" min="3" style="0" width="8.50510204081633"/></cols><sheetData><row r="1" customFormat="false" ht="14.65" hidden="false" customHeight="false" outlineLevel="0" collapsed="false"></row><row r="2" customFormat="false" ht="14.65" hidden="false" customHeight="false" outlineLevel="0" collapsed="false"></row><row r="3" customFormat="false" ht="14.65" hidden="false" customHeight="false" outlineLevel="0" collapsed="false"></row><row r="4" customFormat="false" ht="14.65" hidden="false" customHeight="false" outlineLevel="0" collapsed="false"></row><row r="5" customFormat="false" ht="14.65" hidden="false" customHeight="false" outlineLevel="0" collapsed="false"></row><row r="10" customFormat="false" ht="14.65" hidden="false" customHeight="false" outlineLevel="0" collapsed="false"></row><row r="11" customFormat="false" ht="14.65" hidden="false" customHeight="false" outlineLevel="0" collapsed="false"></row><row r="23" customFormat="false" ht="14.65" hidden="false" customHeight="false" outlineLevel="0" collapsed="false"></row><row r="24" customFormat="false" ht="14.65" hidden="false" customHeight="false" outlineLevel="0" collapsed="false"></row><row r="25" customFormat="false" ht="14.65" hidden="false" customHeight="false" outlineLevel="0" collapsed="false"></row><row r="31" customFormat="false" ht="14.65" hidden="false" customHeight="false" outlineLevel="0" collapsed="false"></row><row r="39" customFormat="false" ht="14.65" hidden="false" customHeight="false" outlineLevel="0" collapsed="false"></row><row r="43" customFormat="false" ht="14.65" hidden="false" customHeight="false" outlineLevel="0" collapsed="false"></row><row r="48" customFormat="false" ht="14.65" hidden="false" customHeight="false" outlineLevel="0" collapsed="false"></row><row r="49" customFormat="false" ht="14.65" hidden="false" customHeight="false" outlineLevel="0" collapsed="false"></row></sheetData><printOptions headings="false" gridLines="false" gridLinesSet="true" horizontalCentered="false" verticalCentered="false"/><pageMargins left="0.7875" right="0.7875" top="1.05277777777778" bottom="1.05277777777778" header="0.7875" footer="0.7875"/><pageSetup paperSize="1" scale="100" firstPageNumber="1" fitToWidth="1" fitToHeight="1" pageOrder="downThenOver" orientation="portrait" usePrinterDefaults="false" blackAndWhite="false" draft="false" cellComments="none" useFirstPageNumber="true" horizontalDpi="300" verticalDpi="300" copies="1"/><headerFooter differentFirst="false" differentOddEven="false"><oddHeader>&amp;C&amp;&quot;Times New Roman,Regular&quot;&amp;12&amp;A</oddHeader><oddFooter>&amp;C&amp;&quot;Times New Roman,Regular&quot;&amp;12Page &amp;P</oddFooter></headerFooter><drawing r:id="rId1"/></worksheet>